mismatch_kernel/__init__.py
mismatch_kernel/mismatch_kernel.py
mismatch_kernel/mismatch_tree.py
mismatch_string_kernel-0.0.1.dist-info/LICENSE
mismatch_string_kernel-0.0.1.dist-info/METADATA
mismatch_string_kernel-0.0.1.dist-info/WHEEL
mismatch_string_kernel-0.0.1.dist-info/top_level.txt
mismatch_string_kernel-0.0.1.dist-info/RECORD
