Metadata-Version: 2.1
Name: mismatch-string-kernel
Version: 0.0.1
Summary: Python3 implementation of mismatch string kernel
Home-page: https://github.com/marcodiri/mismatch_string_kernel
Author: Marco Di Rienzo
Author-email: diridevelops@gmail.com
License: UNKNOWN
Platform: UNKNOWN
Classifier: Programming Language :: Python :: 3
Classifier: License :: OSI Approved :: MIT License
Classifier: Operating System :: OS Independent
Requires-Python: >=3.6
